setup.py
jhsi.egg-info/PKG-INFO
jhsi.egg-info/SOURCES.txt
jhsi.egg-info/dependency_links.txt
jhsi.egg-info/top_level.txt
jhsi.egg-info/zip-safe
mark/__init__.py
mark/label_main.py